{
  "area": [
    {
      "xpos": 27,
      "ypos": 228,
      "width": 138,
      "height": 14,
      "type": "match"
    },
    {
      "xpos": 118,
      "ypos": 243,
      "width": 10,
      "height": 10,
      "type": "match"
    },
    {
      "xpos": 157,
      "ypos": 262,
      "width": 10,
      "height": 10,
      "type": "match"
    },
    {
      "xpos": 110,
      "ypos": 303,
      "width": 10,
      "height": 10,
      "type": "match"
    }
  ],
  "properties": [],
  "tags": [
    "Yast2-Users-Add-User-Created"
  ]
}