{
  "area": [
    {
      "xpos": 305,
      "ypos": 503,
      "width": 86,
      "height": 21,
      "type": "match"
    },
    {
      "xpos": 314,
      "ypos": 572,
      "width": 45,
      "height": 25,
      "type": "match",
      "click_point": {
        "xpos": 22.5,
        "ypos": 12.5
      }
    },
    {
      "xpos": 12,
      "ypos": 124,
      "width": 29,
      "height": 26,
      "type": "match"
    },
    {
      "xpos": 305,
      "ypos": 218,
      "width": 166,
      "height": 26,
      "type": "match"
    }
  ],
  "properties": [],
  "tags": [
    "adminer-click-drop-database-test"
  ]
}