{
  "area": [
    {
      "type": "match",
      "width": 471,
      "xpos": 15,
      "ypos": 722,
      "height": 39
    },
    {
      "width": 390,
      "type": "match",
      "height": 336,
      "ypos": 258,
      "xpos": 107
    },
    {
      "type": "exclude",
      "width": 41,
      "height": 17,
      "xpos": 496,
      "ypos": 231
    }
  ],
  "properties": [],
  "tags": [
    "ENV-DISTRI-opensuse",
    "ENV-LEAP-1",
    "ENV-UEFI-1",
    "bootloader-grub2",
    "inst-bootmenu"
  ]
}