{
  "area": [
    {
      "type": "match",
      "ypos": 148,
      "height": 148,
      "width": 308,
      "xpos": 202,
      "match": 95
    },
    {
      "type": "exclude",
      "ypos": 170,
      "xpos": 525,
      "width": 26,
      "height": 22
    },
    {
      "xpos": 19,
      "ypos": 7,
      "width": 215,
      "height": 77,
      "type": "match",
      "match": 92
    },
    {
      "xpos": 302,
      "ypos": 34,
      "width": 163,
      "height": 37,
      "type": "match",
      "match": 90
    }
  ],
  "properties": [],
  "tags": [
    "ENV-DISTRI-leap-micro",
    "bootloader",
    "inst-bootmenu"
  ]
}