{
  "area": [
    {
      "ypos": 452,
      "click_point": {
        "xpos": 52,
        "ypos": 8
      },
      "width": 95,
      "xpos": 612,
      "type": "match",
      "height": 16
    },
    {
      "height": 23,
      "width": 148,
      "ypos": 373,
      "xpos": 369,
      "type": "match"
    },
    {
      "width": 331,
      "ypos": 413,
      "type": "match",
      "xpos": 366,
      "height": 28
    }
  ],
  "properties": [],
  "tags": [
    "ENV-DESKTOP-gnome",
    "firefox-save-and-quit"
  ]
}