{
  "area": [
    {
      "type": "match",
      "height": 61,
      "width": 175,
      "ypos": 210,
      "xpos": 274
    },
    {
      "ypos": 8,
      "xpos": 265,
      "type": "match",
      "height": 35,
      "width": 445
    },
    {
      "ypos": 734,
      "xpos": 958,
      "type": "match",
      "height": 19,
      "width": 41
    },
    {
      "xpos": 279,
      "ypos": 91,
      "height": 60,
      "width": 130,
      "type": "match"
    }
  ],
  "properties": [],
  "tags": [
    "inst-welcome",
    "installation",
    "languagepicked"
  ]
}