{
  "area": [
    {
      "type": "match",
      "xpos": 240,
      "height": 19,
      "width": 229,
      "ypos": 117
    },
    {
      "width": 231,
      "height": 16,
      "type": "match",
      "xpos": 0,
      "ypos": 135
    },
    {
      "click_point": {
        "xpos": 16.5,
        "ypos": 15
      },
      "ypos": 729,
      "xpos": 695,
      "type": "match",
      "height": 30,
      "width": 33
    }
  ],
  "properties": [],
  "tags": [
    "install-winget-background-wsl"
  ]
}