{
  "area": [
    {
      "height": 29,
      "width": 233,
      "type": "match",
      "ypos": 17,
      "xpos": 4
    },
    {
      "height": 18,
      "type": "match",
      "width": 35,
      "ypos": 734,
      "xpos": 960
    },
    {
      "ypos": 48,
      "xpos": 6,
      "height": 44,
      "width": 145,
      "type": "match"
    },
    {
      "xpos": 152,
      "ypos": 55,
      "width": 122,
      "type": "match",
      "height": 25
    }
  ],
  "properties": [],
  "tags": [
    "ENV-DISTRI-KUBIC",
    "inst-bootloader-settings",
    "inst-bootloader-settings-first_tab_highlighted"
  ]
}