{
  "area": [
    {
      "height": 63,
      "width": 403,
      "xpos": 150,
      "type": "match",
      "ypos": 183
    },
    {
      "type": "match",
      "ypos": 260,
      "xpos": 167,
      "height": 160,
      "width": 214
    },
    {
      "height": 173,
      "xpos": 157,
      "width": 233,
      "type": "match",
      "ypos": 255
    },
    {
      "width": 170,
      "height": 158,
      "xpos": 431,
      "ypos": 261,
      "type": "match"
    },
    {
      "width": 697,
      "height": 69,
      "xpos": 163,
      "type": "match",
      "ypos": 438
    },
    {
      "height": 34,
      "xpos": 631,
      "width": 181,
      "type": "match",
      "ypos": 589
    },
    {
      "height": 39,
      "width": 72,
      "xpos": 828,
      "type": "match",
      "ypos": 588
    }
  ],
  "properties": [],
  "tags": [
    "generic-desktop",
    "opensuse-welcome"
  ]
}