{
  "area": [
    {
      "xpos": 15,
      "ypos": 35,
      "width": 75,
      "height": 14,
      "type": "match"
    },
    {
      "xpos": 95,
      "ypos": 34,
      "width": 100,
      "height": 14,
      "type": "match"
    },
    {
      "xpos": 459,
      "ypos": 673,
      "width": 107,
      "height": 15,
      "type": "match"
    },
    {
      "xpos": 427,
      "ypos": 690,
      "width": 164,
      "height": 16,
      "type": "match"
    }
  ],
  "properties": [],
  "tags": [
    "inst-suggested-partitioning-step"
  ]
}