{
  "area": [
    {
      "ypos": 418,
      "xpos": 451,
      "width": 39,
      "type": "match",
      "height": 20
    },
    {
      "ypos": 419,
      "xpos": 526,
      "width": 46,
      "height": 19,
      "type": "match"
    },
    {
      "width": 149,
      "height": 18,
      "type": "match",
      "xpos": 481,
      "ypos": 381
    },
    {
      "width": 108,
      "height": 17,
      "type": "match",
      "xpos": 45,
      "ypos": 244
    }
  ],
  "properties": [],
  "tags": [
    "online-repos-popup"
  ]
}