{
  "area": [
    {
      "ypos": 1,
      "xpos": 2,
      "width": 185,
      "height": 207,
      "type": "match"
    },
    {
      "type": "match",
      "xpos": 246,
      "ypos": 433,
      "height": 35,
      "width": 164
    },
    {
      "xpos": 448,
      "ypos": 243,
      "width": 84,
      "height": 17,
      "type": "match"
    }
  ],
  "properties": [],
  "tags": [
    "ENV-DESKTOP-kde",
    "ooffice",
    "ooffice-tip-of-the-day",
    "oowriter",
    "oowriter-first-run",
    "test-ooffice-1"
  ]
}