{
  "area": [
    {
      "width": 200,
      "type": "match",
      "ypos": 64,
      "xpos": 2,
      "height": 184
    },
    {
      "width": 160,
      "type": "match",
      "height": 37,
      "ypos": 125,
      "xpos": 367
    },
    {
      "width": 174,
      "type": "match",
      "height": 40,
      "ypos": 280,
      "xpos": 55
    }
  ],
  "properties": [],
  "tags": [
    "ENV-DESKTOP-gnome",
    "ooffice",
    "ooffice-tip-of-the-day",
    "oowriter",
    "test-ooffice-1"
  ]
}