{
  "area": [
    {
      "ypos": 173,
      "xpos": 581,
      "height": 13,
      "width": 128,
      "type": "match"
    },
    {
      "xpos": 329,
      "ypos": 173,
      "type": "match",
      "height": 29,
      "width": 157
    },
    {
      "ypos": 203,
      "xpos": 645,
      "height": 29,
      "width": 231,
      "type": "match"
    },
    {
      "ypos": 202,
      "xpos": 327,
      "width": 247,
      "height": 30,
      "type": "match"
    }
  ],
  "properties": [],
  "tags": [
    "partitioning-full-lvm-encrypt"
  ]
}