{
  "area": [
    {
      "xpos": 359,
      "height": 29,
      "type": "match",
      "width": 202,
      "ypos": 259
    },
    {
      "xpos": 363,
      "height": 24,
      "type": "match",
      "ypos": 335,
      "width": 106
    },
    {
      "width": 76,
      "ypos": 377,
      "height": 22,
      "type": "match",
      "xpos": 369
    },
    {
      "xpos": 516,
      "height": 32,
      "type": "match",
      "width": 239,
      "ypos": 496
    }
  ],
  "properties": [],
  "tags": [
    "Policykit",
    "Policykit-root",
    "root-auth-dialog"
  ]
}