{
  "area": [
    {
      "ypos": 231,
      "xpos": 372,
      "width": 280,
      "type": "match",
      "height": 30
    },
    {
      "ypos": 282,
      "type": "match",
      "height": 15,
      "xpos": 363,
      "width": 298
    },
    {
      "ypos": 534,
      "width": 403,
      "xpos": 309,
      "click_point": {
        "xpos": 307.5,
        "ypos": 14.5
      },
      "height": 31,
      "type": "match"
    }
  ],
  "properties": [],
  "tags": [
    "polkit-unmount-auth-required"
  ]
}