{
  "area": [
    {
      "xpos": 451,
      "ypos": 69,
      "width": 124,
      "height": 27,
      "type": "match"
    },
    {
      "xpos": 206,
      "ypos": 118,
      "width": 65,
      "height": 23,
      "type": "match"
    },
    {
      "xpos": 854,
      "ypos": 691,
      "width": 53,
      "height": 22,
      "type": "match",
      "click_point": {
        "xpos": 26.5,
        "ypos": 11
      }
    }
  ],
  "properties": [],
  "tags": [
    "rstudio_desktop-create-new-project_select-HOME"
  ]
}