{
  "area": [
    {
      "ypos": 146,
      "xpos": 43,
      "width": 953,
      "type": "match",
      "height": 458,
      "match": 90
    },
    {
      "width": 15,
      "type": "match",
      "height": 59,
      "xpos": 427,
      "ypos": 81,
      "match": 90
    },
    {
      "height": 53,
      "type": "match",
      "width": 50,
      "xpos": 579,
      "ypos": 84,
      "match": 90
    },
    {
      "ypos": 147,
      "xpos": 229,
      "type": "exclude",
      "width": 558,
      "height": 90
    }
  ],
  "properties": [],
  "tags": [
    "ENV-DESKTOP-kde",
    "screenlock"
  ]
}