{
  "area": [
    {
      "width": 149,
      "type": "match",
      "xpos": 122,
      "ypos": 111,
      "height": 17
    },
    {
      "type": "match",
      "xpos": 179,
      "ypos": 143,
      "height": 21,
      "width": 142
    },
    {
      "ypos": 145,
      "xpos": 436,
      "type": "match",
      "height": 19,
      "width": 142
    },
    {
      "ypos": 145,
      "type": "match",
      "xpos": 690,
      "height": 17,
      "width": 161
    },
    {
      "height": 55,
      "xpos": 137,
      "type": "match",
      "ypos": 198,
      "width": 133
    },
    {
      "width": 183,
      "type": "match",
      "xpos": 137,
      "ypos": 274,
      "height": 49
    }
  ],
  "properties": [],
  "tags": [
    "ENV-ARCH-aarch64",
    "yast2-bootloader-ui"
  ]
}